{"otherData": {},"traceEvents":[{},{"cat":"function","dur":0,"name":"OGLE::Application::~Application(void)","ph":"X","pid":0,"tid":23252,"ts":90312180581.500},{"cat":"function","dur":1995,"name":"void OGLE::ImGuiLayer::OnDetach(void)","ph":"X","pid":0,"tid":23252,"ts":90312180666.800},{"cat":"function","dur":14035,"name":"void OGLE::WindowsWindow::Shutdown(void)","ph":"X","pid":0,"tid":23252,"ts":90312182763.400},{"cat":"function","dur":14176,"name":"OGLE::WindowsWindow::~WindowsWindow(void)","ph":"X","pid":0,"tid":23252,"ts":90312182763.200}]}